verify_email/__init__.py
verify_email/admin.py
verify_email/app_configurations.py
verify_email/apps.py
verify_email/confirm.py
verify_email/email_handler.py
verify_email/errors.py
verify_email/forms.py
verify_email/models.py
verify_email/signals.py
verify_email/tests.py
verify_email/token_manager.py
verify_email/urls.py
verify_email/views.py
verify_email/locale/de/LC_MESSAGES/django.mo
verify_email/locale/de/LC_MESSAGES/django.po
verify_email/locale/es/LC_MESSAGES/django.mo
verify_email/locale/es/LC_MESSAGES/django.po
verify_email/locale/fr/LC_MESSAGES/django.mo
verify_email/locale/fr/LC_MESSAGES/django.po
verify_email/locale/it/LC_MESSAGES/django.mo
verify_email/locale/it/LC_MESSAGES/django.po
verify_email/locale/pt/LC_MESSAGES/django.mo
verify_email/locale/pt/LC_MESSAGES/django.po
verify_email/migrations/0001_initial.py
verify_email/migrations/__init__.py
verify_email/templates/email_index.html
verify_email/templates/verify_email/email_verification_failed.html
verify_email/templates/verify_email/email_verification_msg.html
verify_email/templates/verify_email/email_verification_successful.html
verify_email/templates/verify_email/link_expired.html
verify_email/templates/verify_email/new_email_sent.html
verify_email/templates/verify_email/request_new_email.html
django_email_validation-2.1.1.dist-info/METADATA
django_email_validation-2.1.1.dist-info/WHEEL
django_email_validation-2.1.1.dist-info/licenses/LICENSE
django_email_validation-2.1.1.dist-info/RECORD
