Metadata-Version: 2.4
Name: django-email-validation
Version: 2.1.1
Summary:  A Django app for email verification.
Project-URL: Homepage, https://github.com/foo290/Django-Verify-Email/
Project-URL: Repository, https://github.com/foo290/Django-Verify-Email.git
Project-URL: Issues, https://github.com/foo290/Django-Verify-Email//issues
Project-URL: Download, https://github.com/foo290/Django-Verify-Email/archive/refs/tags/2.0.4.tar.gz
Author-email: Nitin Sharma <ns290670@gamil.com>, Olivier LEVILLAIN <levillain.olivier@gmail.com>
License-File: LICENSE
Keywords: check,email,validation
Classifier: Environment :: Web Environment
Classifier: Framework :: Django CMS :: 3.8
Classifier: Intended Audience :: Developers
Classifier: License :: OSI Approved :: MIT License
Classifier: Operating System :: OS Independent
Classifier: Programming Language :: Python :: 3.6
Requires-Python: >=3.6
Requires-Dist: django
